namedpath.py
namedpath-0.2.3.dist-info/LICENSE
namedpath-0.2.3.dist-info/METADATA
namedpath-0.2.3.dist-info/WHEEL
namedpath-0.2.3.dist-info/RECORD
